{"files":{"pages/index.vue":{"frameworks":["@unocss/preset-icons","pg.insight.events","@vue/devtools","pg.vue.tree.painter","project","pg.css.grid","@nuxt/devtools","pg.image.overlay","pg.code-validator","pg.project.items","pg.asset.manager","app_designer","vue","nuxt","@pinegrow/nuxt-module","pg.html"]},"components/media/Hero.vue":{"frameworks":["@unocss/preset-icons","@vue/devtools","@nuxt/devtools","pg.insight.events","pg.vue.tree.painter","pg.css.grid","@pinegrow/nuxt-module","pg.image.overlay","nuxt","pg.code-validator","pg.project.items","pg.asset.manager","app_designer","project","vue","tw.flowbite","pg.html"]},"pages/[type]/[id].vue":{"frameworks":["@vue/devtools","@nuxt/devtools","nuxt-icon","@pinegrow/nuxt-module","nuxt","vue","app_designer","project","pg.insight.events","pg.css.grid","pg.image.overlay","pg.code-validator","pg.project.items","pg.asset.manager","pg.html"]}},"template_framework_id":"vue","open-pages":["components/media/Hero.vue"],"urls":{"pages/index.vue":{"open-page-views":[{"w":1024,"h":0}]},"components/media/Hero.vue":{"open-page-views":[{"w":1024,"h":0}]},"pages/%5Btype%5D/%5Bid%5D.vue":{"open-page-views":[{"w":1024,"h":0}]}},"breakpoints":[],"frameworks":["@unocss/preset-icons","@vue/devtools","@nuxt/devtools","pg.insight.events","pg.vue.tree.painter","pg.css.grid","@pinegrow/nuxt-module","pg.image.overlay","nuxt","pg.code-validator","pg.project.items","pg.asset.manager","app_designer","project","vue","tw.flowbite","pg.html"]}